[
  {
    "name": "Americano",
    "ingredient":
        [
          {
            "type": "water",
            "ratio": 7
          },
          {
            "type": "espresso",
            "ratio": 3
          }
        ]
  },
  {
    "name": "Latte",
    "ingredient":
    [
      {
        "type": "milk",
        "ratio": 7
      },
      {
        "type": "espresso",
        "ratio": 3
      }
    ]
  },
  {
    "name": "Favourite",
    "ingredient":
    [
      {
        "type": "milk",
        "ratio": 4
      },
      {
        "type": "espresso",
        "ratio": 3
      },
      {
        "type": "hotChocolate",
        "ratio": 3
      }
    ]
  },
  {
    "name": "Mocha",
    "ingredient":
    [
      {
        "type": "hotChocolate",
        "ratio": 6
      },
      {
        "type": "espresso",
        "ratio": 4
      }
    ]
  }
]
